libhomeseer/__init__.py
libhomeseer/const.py
libhomeseer/devices.py
libhomeseer/errors.py
libhomeseer/events.py
libhomeseer/helpers.py
libhomeseer/homeseer.py
libhomeseer/listener.py
libhomeseer-1.3.0.dist-info/LICENSE
libhomeseer-1.3.0.dist-info/METADATA
libhomeseer-1.3.0.dist-info/WHEEL
libhomeseer-1.3.0.dist-info/top_level.txt
libhomeseer-1.3.0.dist-info/RECORD
