Metadata-Version: 2.1
Name: libhomeseer
Version: 1.3.0
Summary: Python3 async library for interacting with HomeSeer HS3 and HS4 via JSON and ASCII
Home-page: https://github.com/marthoc/libhomeseer
Author: Mark Coombes
Author-email: mark@markcoombes.ca
License: UNKNOWN
Platform: UNKNOWN
Classifier: Intended Audience :: Developers
Classifier: Programming Language :: Python
Classifier: Programming Language :: Python :: 3
Classifier: License :: OSI Approved :: MIT License
Classifier: Operating System :: OS Independent
Classifier: Topic :: Software Development :: Libraries :: Python Modules
Requires-Dist: asyncio
Requires-Dist: aiohttp
